dj_txmoney-0.6.0.dist-info/DESCRIPTION.rst
dj_txmoney-0.6.0.dist-info/METADATA
dj_txmoney-0.6.0.dist-info/RECORD
dj_txmoney-0.6.0.dist-info/WHEEL
dj_txmoney-0.6.0.dist-info/metadata.json
dj_txmoney-0.6.0.dist-info/top_level.txt
tests/__init__.py
tests/test_fields.py
tests/test_money.py
tests/test_rates.py
tests/test_rendering.py
tests/test_rest.py
tests/testapp/__init__.py
tests/testapp/models.py
tests/testapp/serializers.py
tests/testapp/settings.py
tests/testapp/urls.py
tests/testapp/views.py
txmoney/__init__.py
txmoney/settings.py
txmoney/utils.py
txmoney/money/__init__.py
txmoney/money/exceptions.py
txmoney/money/money.py
txmoney/money/models/__init__.py
txmoney/money/models/fields.py
txmoney/rates/__init__.py
txmoney/rates/apps.py
txmoney/rates/backends.py
txmoney/rates/exceptions.py
txmoney/rates/models.py
txmoney/rates/tasks.py
txmoney/rates/management/__init__.py
txmoney/rates/management/commands/__init__.py
txmoney/rates/management/commands/update_rates.py
txmoney/rates/migrations/0001_initial.py
txmoney/rates/migrations/__init__.py
txmoney/rest/__init__.py
txmoney/rest/apps.py
txmoney/rest/fields.py
