Metadata-Version: 2.0
Name: dj-txmoney
Version: 0.6.0
Summary: Adds support for working with money, currencies and rates.
Home-page: https://github.com/txerpa/dj-txmoney
Author: Mateu Cànaves Albertí
Author-email: mateu.canaves@gmail.com
License: BSD
Keywords: dj-txmoney,txmoney,money,currency,finance
Platform: UNKNOWN
Classifier: Development Status :: 4 - Beta
Classifier: Framework :: Django
Classifier: Framework :: Django :: 1.8
Classifier: Framework :: Django :: 1.9
Classifier: Intended Audience :: Developers
Classifier: License :: OSI Approved :: BSD License
Classifier: Natural Language :: English
Classifier: Programming Language :: Python :: 2
Classifier: Programming Language :: Python :: 2.7
Classifier: Programming Language :: Python :: 3
Classifier: Programming Language :: Python :: 3.5
Requires-Dist: Django (<1.10,>=1.8.1)
Requires-Dist: six
Provides-Extra: docs
Requires-Dist: Sphinx (>=1.3.1); extra == 'docs'
Requires-Dist: pyenchant (==1.6.6); extra == 'docs'
Requires-Dist: sphinx-autobuild (>=0.5.2); extra == 'docs'
Requires-Dist: sphinx-rtd-theme (>=0.1.8); extra == 'docs'
Requires-Dist: sphinxcontrib-spelling (==2.1.1); extra == 'docs'
Provides-Extra: postgresql
Requires-Dist: psycopg2 (>=2.6); extra == 'postgresql'
Provides-Extra: rates
Requires-Dist: celery (>=3.0.0); extra == 'rates'
Provides-Extra: rest
Requires-Dist: djangorestframework (>=3.1.0); extra == 'rest'
Provides-Extra: testing
Requires-Dist: coverage (>=4.1); extra == 'testing'
Requires-Dist: flake8 (>=2.2.0); extra == 'testing'
Requires-Dist: mock; extra == 'testing'
Requires-Dist: pytest; extra == 'testing'
Requires-Dist: pytest-django; extra == 'testing'
Requires-Dist: pytest-sugar; extra == 'testing'
Requires-Dist: tox; extra == 'testing'
